botapi/__init__.py
botapi/__init__.pyi
botapi/bot.py
botapi/core.py
botapi/dispatchers/__init__.py
botapi/dispatchers/__init__.pyi
botapi/dispatchers/common.py
botapi/dispatchers/get_updates_handler.py
botapi/dispatchers/redis_pubsub_handler.py
botapi/enums.py
botapi/errors.py
botapi/internals.py
botapi/methods.py
botapi/types.py
botapi_py-1.5.3.dist-info/WHEEL
botapi_py-1.5.3.dist-info/METADATA
botapi_py-1.5.3.dist-info/RECORD
