Metadata-Version: 2.3
Name: botapi-py
Version: 1.5.3
Summary: A simple and flexible Python library to conveniently build fast Telegram bots using the Bot API.
Requires-Dist: httpx>=0.28.1
Requires-Dist: pydantic>=2.12.0
Requires-Dist: orjson>=3.11.3 ; extra == 'redis'
Requires-Dist: redis>=6.4.0 ; extra == 'redis'
Requires-Python: >=3.12
Project-URL: Telegram BotAPI Docs, https://core.telegram.org/bots/api
Provides-Extra: redis
